LICENSE
README.md
gitignore_parser.py
pyproject.toml
setup.cfg
setup.py
gitignore_parser.egg-info/PKG-INFO
gitignore_parser.egg-info/SOURCES.txt
gitignore_parser.egg-info/dependency_links.txt
gitignore_parser.egg-info/top_level.txt